snekilings/__init__.py
snekilings/__main__.py
snekilings/execution.py
snekilings/exercise.py
snekilings/exercises_handler.py
snekilings/logger.py
snekilings/exercises/0_intro/main.py
snekilings/exercises/1_hello_world/main.py
snekilings/exercises/2_assign_variable/main.py
snekilings/exercises/3_assign_variable_wo_equal/main.py
snekilings/exercises/4_basic_math/main.py
snekilings/watchdog/__init__.py
snekilings/watchdog/watch_exercise.py
snekilings/watchdog/event_handlers/__init__.py
snekilings/watchdog/event_handlers/logging_handler.py
snekilings/watchdog/event_handlers/modify_handler.py
snekilings-1.0.0.dev2.dist-info/LICENSE
snekilings-1.0.0.dev2.dist-info/METADATA
snekilings-1.0.0.dev2.dist-info/WHEEL
snekilings-1.0.0.dev2.dist-info/entry_points.txt
snekilings-1.0.0.dev2.dist-info/top_level.txt
snekilings-1.0.0.dev2.dist-info/RECORD
