Metadata-Version: 2.1
Name: snekilings
Version: 1.0.0.dev2
Summary: 🐍 A collection of small exercises to assist beginners at reading and writing Python code.
Author-email: Goldy <goldy@devgoldy.xyz>
License: MIT License
Project-URL: GitHub, https://github.com/THEGOLDENPRO/snekilings
Project-URL: BugTracker, https://github.com/THEGOLDENPRO/snekilings/issues
Keywords: python exercises,python beginners
Classifier: Operating System :: Microsoft :: Windows :: Windows 11
Classifier: Operating System :: Microsoft :: Windows :: Windows 10
Classifier: Operating System :: POSIX :: Linux
Classifier: License :: OSI Approved :: MIT License
Classifier: Programming Language :: Python :: 3.8
Classifier: Programming Language :: Python :: 3.9
Classifier: Programming Language :: Python :: 3.10
Classifier: Programming Language :: Python :: 3.11
Classifier: Programming Language :: Python :: 3.12
Requires-Python: >=3.8
License-File: LICENSE
Requires-Dist: typer
Requires-Dist: devgoldyutils
Requires-Dist: watchdog
Requires-Dist: pytest
Provides-Extra: dev
Requires-Dist: ruff ; extra == 'dev'
Requires-Dist: build ; extra == 'dev'
